oarepo_requests/__init__.py
oarepo_requests/cli.py
oarepo_requests/config.py
oarepo_requests/errors.py
oarepo_requests/ext.py
oarepo_requests/identity_to_entity_references.py
oarepo_requests/invenio_patches.py
oarepo_requests/models.py
oarepo_requests/proxies.py
oarepo_requests/receiver.py
oarepo_requests/snapshots.py
oarepo_requests/typing.py
oarepo_requests/utils.py
oarepo_requests/actions/__init__.py
oarepo_requests/actions/cascade_events.py
oarepo_requests/actions/components.py
oarepo_requests/actions/delete_draft.py
oarepo_requests/actions/delete_published_record.py
oarepo_requests/actions/edit_topic.py
oarepo_requests/actions/generic.py
oarepo_requests/actions/new_version.py
oarepo_requests/actions/publish_draft.py
oarepo_requests/actions/publish_new_version.py
oarepo_requests/actions/record_snapshot_mixin.py
oarepo_requests/alembic/_57aebe908bcb_create_snapshot_table.py
oarepo_requests/alembic/_985368490c5b_create_oarepo_requests_branch.py
oarepo_requests/alembic/__init__.py
oarepo_requests/notifications/__init__.py
oarepo_requests/notifications/generators.py
oarepo_requests/notifications/builders/__init__.py
oarepo_requests/notifications/builders/delete_published_record.py
oarepo_requests/notifications/builders/escalate.py
oarepo_requests/notifications/builders/oarepo.py
oarepo_requests/notifications/builders/publish.py
oarepo_requests/resolvers/__init__.py
oarepo_requests/resolvers/interface.py
oarepo_requests/resolvers/service_result.py
oarepo_requests/resolvers/ui.py
oarepo_requests/resolvers/user_notification_resolver.py
oarepo_requests/resources/__init__.py
oarepo_requests/resources/ui.py
oarepo_requests/resources/draft/__init__.py
oarepo_requests/resources/draft/config.py
oarepo_requests/resources/draft/resource.py
oarepo_requests/resources/draft/types/__init__.py
oarepo_requests/resources/draft/types/config.py
oarepo_requests/resources/draft/types/resource.py
oarepo_requests/resources/events/__init__.py
oarepo_requests/resources/events/config.py
oarepo_requests-2.5.8.dist-info/licenses/LICENSE
oarepo_requests-2.5.8.dist-info/METADATA
oarepo_requests-2.5.8.dist-info/WHEEL
oarepo_requests-2.5.8.dist-info/entry_points.txt
oarepo_requests-2.5.8.dist-info/top_level.txt
oarepo_requests-2.5.8.dist-info/RECORD
