Metadata-Version: 2.4
Name: oarepo-requests
Version: 2.5.8
License-File: LICENSE
Requires-Dist: invenio-requests
Requires-Dist: oarepo-runtime
Requires-Dist: oarepo-workflows
Provides-Extra: tests
Requires-Dist: deepdiff; extra == "tests"
Requires-Dist: oarepo-ui; extra == "tests"
Requires-Dist: pytest-oarepo[requests]; extra == "tests"
Dynamic: license-file
